simplyrestful/__init__.py
simplyrestful/app.py
simplyrestful/authenticators.py
simplyrestful/authorizers.py
simplyrestful/database.py
simplyrestful/exceptions.py
simplyrestful/filtering.py
simplyrestful/resources.py
simplyrestful/serializers.py
simplyrestful/settings.py
simplyrestful/util.py
simplyrestful/validators.py
simplyrestful/models/__init__.py
simplyrestful/models/geometry.py
simplyrestful/models/model.py
simplyrestful-0.2.2.dist-info/DESCRIPTION.rst
simplyrestful-0.2.2.dist-info/METADATA
simplyrestful-0.2.2.dist-info/RECORD
simplyrestful-0.2.2.dist-info/WHEEL
simplyrestful-0.2.2.dist-info/metadata.json
simplyrestful-0.2.2.dist-info/top_level.txt
