Metadata-Version: 2.0
Name: simplyrestful
Version: 0.2.2
Summary: A simple framework to quickly implement ReSTful APIs.
Home-page: https://github.com/gabrielbazan/simply-restful/
Author: Gabriel Jose Bazan
Author-email: gbazan@outlook.com
License: MIT
Download-URL: https://github.com/gabrielbazan/simply-restful/
Keywords: Simply ReSTful REST API
Platform: all
Requires-Dist: flask
Requires-Dist: flask-restful
Requires-Dist: geoalchemy2
Requires-Dist: geojson
Requires-Dist: psycopg2
Requires-Dist: shapely
Requires-Dist: sqlalchemy
